MANIFEST.in
setup.py
krisk/__init__.py
krisk/util.py
krisk.egg-info/PKG-INFO
krisk.egg-info/SOURCES.txt
krisk.egg-info/dependency_links.txt
krisk.egg-info/top_level.txt
krisk/chart/__init__.py
krisk/chart/api.py
krisk/chart/core.py
krisk/plot/__init__.py
krisk/plot/api.py
krisk/plot/make_bar_line.py
krisk/plot/make_chart.py
krisk/plot/make_scatter_geo.py
krisk/static/dark.js
krisk/static/echarts.min.js
krisk/static/infographic.js
krisk/static/krisk-require.js
krisk/static/krisk.js
krisk/static/macarons.js
krisk/static/on_event.js
krisk/static/roma.js
krisk/static/shine.js
krisk/static/template.html
krisk/static/vintage.js
krisk/tests/conftest.py
krisk/tests/test_chart.py
krisk/tests/test_plot.py
krisk/tests/test_template.py
krisk/tests/test_title_legend_toolbox.py
krisk/tests/test_tooltip.py