Metadata-Version: 1.1
Name: krisk
Version: 0.3.0
Summary: Echarts Statistical Visualization for Python Data Science
Home-page: https://github.com/napjon/krisk/
Author: Jonathan Napitupulu
Author-email: napitupulu.jon@gmail.com
License: BSD (3-clause)
Download-URL: https://github.com/napjon/krisk/
Platform: UNKNOWN
Classifier: Development Status :: 4 - Beta
Classifier: Operating System :: OS Independent
Classifier: Intended Audience :: Science/Research
Classifier: License :: OSI Approved :: BSD License
Classifier: Programming Language :: Python :: 3.5
